Workbook

Sheet Painel
A1: Painel de Estudos – Especialista em Power BI e Excel
A2: Tudo nesta aba é calculado automaticamente. Atualize apenas a aba Checklist (Status) e a aba Diario (horas).
A3: Tópicos | C3: Concluídos | E3: % Concluído | G3: Horas estudadas
A4: =COUNTA(Checklist!$A$2:$A$62) -> 61 | C4: =COUNTIF(Checklist!$G$2:$G$62,"Concluído") -> 0 | E4: =IF(A4=0,0,C4/A4) -> 0 | G4: =SUM(Diario!$D$2:$D$400) -> 0
A6: Status dos tópicos
A7: Não iniciado | B7: =COUNTIF(Checklist!$G$2:$G$62,A7) -> 61
A8: Estudando | B8: =COUNTIF(Checklist!$G$2:$G$62,A8) -> 0
A9: Revisar | B9: =COUNTIF(Checklist!$G$2:$G$62,A9) -> 0
A10: Concluído | B10: =COUNTIF(Checklist!$G$2:$G$62,A10) -> 0
A12: Progresso por bloco de conhecimento
A13: Bloco | B13: Tópicos | C13: Concluídos | D13: % Concluído | E13: Horas
A14: Excel | B14: =COUNTIF(Checklist!$C$2:$C$62,A14) -> 16 | C14: =COUNTIFS(Checklist!$C$2:$C$62,A14,Checklist!$G$2:$G$62,"Concluído") -> 0 | D14: =IF(B14=0,0,C14/B14) -> 0 | E14: =SUMIFS(Checklist!$J$2:$J$62,Checklist!$C$2:$C$62,A14) -> 0
A15: Power Query | B15: =COUNTIF(Checklist!$C$2:$C$62,A15) -> 8 | C15: =COUNTIFS(Checklist!$C$2:$C$62,A15,Checklist!$G$2:$G$62,"Concluído") -> 0 | D15: =IF(B15=0,0,C15/B15) -> 0 | E15: =SUMIFS(Checklist!$J$2:$J$62,Checklist!$C$2:$C$62,A15) -> 0
A16: Power BI | B16: =COUNTIF(Checklist!$C$2:$C$62,A16) -> 19 | C16: =COUNTIFS(Checklist!$C$2:$C$62,A16,Checklist!$G$2:$G$62,"Concluído") -> 0 | D16: =IF(B16=0,0,C16/B16) -> 0 | E16: =SUMIFS(Checklist!$J$2:$J$62,Checklist!$C$2:$C$62,A16) -> 0
A17: Dados | B17: =COUNTIF(Checklist!$C$2:$C$62,A17) -> 6 | C17: =COUNTIFS(Checklist!$C$2:$C$62,A17,Checklist!$G$2:$G$62,"Concluído") -> 0 | D17: =IF(B17=0,0,C17/B17) -> 0 | E17: =SUMIFS(Checklist!$J$2:$J$62,Checklist!$C$2:$C$62,A17) -> 0
A18: Python | B18: =COUNTIF(Checklist!$C$2:$C$62,A18) -> 4 | C18: =COUNTIFS(Checklist!$C$2:$C$62,A18,Checklist!$G$2:$G$62,"Concluído") -> 0 | D18: =IF(B18=0,0,C18/B18) -> 0 | E18: =SUMIFS(Checklist!$J$2:$J$62,Checklist!$C$2:$C$62,A18) -> 0
A19: Negócio | B19: =COUNTIF(Checklist!$C$2:$C$62,A19) -> 8 | C19: =COUNTIFS(Checklist!$C$2:$C$62,A19,Checklist!$G$2:$G$62,"Concluído") -> 0 | D19: =IF(B19=0,0,C19/B19) -> 0 | E19: =SUMIFS(Checklist!$J$2:$J$62,Checklist!$C$2:$C$62,A19) -> 0
A22: Liberação dos pacotes para venda
A23: Nível Básico liberado = todos os tópicos Básico e Intermediário do pacote concluídos. Completo = todos, inclusive os Avançados.
A24: Pacote | B24: Tópicos | C24: Concluídos | D24: % Concluído | E24: Nível Básico | F24: Completo (Padrão/Premium)
A25: Pacote 1 – Limpeza e Padronização | B25: =COUNTIF(Checklist!$D$2:$D$62,"*1*")+COUNTIF(Checklist!$D$2:$D$62,"Todos") -> 21 | C25: =COUNTIFS(Checklist!$D$2:$D$62,"*1*",Checklist!$G$2:$G$62,"Concluído")+COUNTIFS(Checklist!$D$2:$D$62,"Todos",Checklist!$G$2:$G$62,"Concluído") -> 0 | D25: =IF(B25=0,0,C25/B25) -> 0 | E25: =IF(COUNTIFS(Checklist!$D$2:$D$62,"*1*",Checklist!$F$2:$F$62,"<>Avançado",Checklist!$G$2:$G$62,"Concluído")+COUNTIFS(Checklist!$D$2:$D$62,"Todos",Checklist!$F$2:$F$62,"<>Avançado",Checklist!$G$2:$G$62,"Concluído")=COUNTIFS(Checklist!$D$2:$D$62,"*1*",Checklist!$F$2:$F$62,"<>Avançado")+COUNTIFS(Checklist!$D$2:$D$62,"Todos",Checklist!$F$2:$F$62,"<>Avançado"),"✔ PODE VENDER","Em preparação") -> Em preparação | F25: =IF(C25=B25,"✔ PODE VENDER","Em preparação") -> Em preparação
A26: Pacote 2 – Vendas e Estoque no Excel | B26: =COUNTIF(Checklist!$D$2:$D$62,"*2*")+COUNTIF(Checklist!$D$2:$D$62,"Todos") -> 24 | C26: =COUNTIFS(Checklist!$D$2:$D$62,"*2*",Checklist!$G$2:$G$62,"Concluído")+COUNTIFS(Checklist!$D$2:$D$62,"Todos",Checklist!$G$2:$G$62,"Concluído") -> 0 | D26: =IF(B26=0,0,C26/B26) -> 0 | E26: =IF(COUNTIFS(Checklist!$D$2:$D$62,"*2*",Checklist!$F$2:$F$62,"<>Avançado",Checklist!$G$2:$G$62,"Concluído")+COUNTIFS(Checklist!$D$2:$D$62,"Todos",Checklist!$F$2:$F$62,"<>Avançado",Checklist!$G$2:$G$62,"Concluído")=COUNTIFS(Checklist!$D$2:$D$62,"*2*",Checklist!$F$2:$F$62,"<>Avançado")+COUNTIFS(Checklist!$D$2:$D$62,"Todos",Checklist!$F$2:$F$62,"<>Avançado"),"✔ PODE VENDER","Em preparação") -> Em preparação | F26: =IF(C26=B26,"✔ PODE VENDER","Em preparação") -> Em preparação
A27: Pacote 3 – Dashboard Power BI | B27: =COUNTIF(Checklist!$D$2:$D$62,"*3*")+COUNTIF(Checklist!$D$2:$D$62,"Todos") -> 35 | C27: =COUNTIFS(Checklist!$D$2:$D$62,"*3*",Checklist!$G$2:$G$62,"Concluído")+COUNTIFS(Checklist!$D$2:$D$62,"Todos",Checklist!$G$2:$G$62,"Concluído") -> 0 | D27: =IF(B27=0,0,C27/B27) -> 0 | E27: =IF(COUNTIFS(Checklist!$D$2:$D$62,"*3*",Checklist!$F$2:$F$62,"<>Avançado",Checklist!$G$2:$G$62,"Concluído")+COUNTIFS(Checklist!$D$2:$D$62,"Todos",Checklist!$F$2:$F$62,"<>Avançado",Checklist!$G$2:$G$62,"Concluído")=COUNTIFS(Checklist!$D$2:$D$62,"*3*",Checklist!$F$2:$F$62,"<>Avançado")+COUNTIFS(Checklist!$D$2:$D$62,"Todos",Checklist!$F$2:$F$62,"<>Avançado"),"✔ PODE VENDER","Em preparação") -> Em preparação | F27: =IF(C27=B27,"✔ PODE VENDER","Em preparação") -> Em preparação
A28: Pacote 4 – Manutenção Recorrente | B28: =COUNTIF(Checklist!$D$2:$D$62,"*4*")+COUNTIF(Checklist!$D$2:$D$62,"Todos") -> 10 | C28: =COUNTIFS(Checklist!$D$2:$D$62,"*4*",Checklist!$G$2:$G$62,"Concluído")+COUNTIFS(Checklist!$D$2:$D$62,"Todos",Checklist!$G$2:$G$62,"Concluído") -> 0 | D28: =IF(B28=0,0,C28/B28) -> 0 | E28: =IF(COUNTIFS(Checklist!$D$2:$D$62,"*4*",Checklist!$F$2:$F$62,"<>Avançado",Checklist!$G$2:$G$62,"Concluído")+COUNTIFS(Checklist!$D$2:$D$62,"Todos",Checklist!$F$2:$F$62,"<>Avançado",Checklist!$G$2:$G$62,"Concluído")=COUNTIFS(Checklist!$D$2:$D$62,"*4*",Checklist!$F$2:$F$62,"<>Avançado")+COUNTIFS(Checklist!$D$2:$D$62,"Todos",Checklist!$F$2:$F$62,"<>Avançado"),"✔ PODE VENDER","Em preparação") -> Em preparação | F28: =IF(C28=B28,"✔ PODE VENDER","Em preparação") -> Em preparação
A29: Extras – Python e automação | B29: =COUNTIF(Checklist!$D$2:$D$62,"*E*")+COUNTIF(Checklist!$D$2:$D$62,"Todos") -> 10 | C29: =COUNTIFS(Checklist!$D$2:$D$62,"*E*",Checklist!$G$2:$G$62,"Concluído")+COUNTIFS(Checklist!$D$2:$D$62,"Todos",Checklist!$G$2:$G$62,"Concluído") -> 0 | D29: =IF(B29=0,0,C29/B29) -> 0 | E29: =IF(COUNTIFS(Checklist!$D$2:$D$62,"*E*",Checklist!$F$2:$F$62,"<>Avançado",Checklist!$G$2:$G$62,"Concluído")+COUNTIFS(Checklist!$D$2:$D$62,"Todos",Checklist!$F$2:$F$62,"<>Avançado",Checklist!$G$2:$G$62,"Concluído")=COUNTIFS(Checklist!$D$2:$D$62,"*E*",Checklist!$F$2:$F$62,"<>Avançado")+COUNTIFS(Checklist!$D$2:$D$62,"Todos",Checklist!$F$2:$F$62,"<>Avançado"),"✔ PODE VENDER","Em preparação") -> Em preparação | F29: =IF(C29=B29,"✔ PODE VENDER","Em preparação") -> Em preparação

Sheet LEIA-ME
A1: Acompanhamento de Estudos – Power BI e Excel
A2: 61 tópicos organizados em 8 semanas, ligados aos 4 pacotes do portfólio e à Base_Ficticia_ECommerce.xlsx.
A4: ABA | B4: COMO USAR
A5: Painel | B5: Visão geral automática: % concluído, horas, progresso por bloco e quais pacotes já podem ser vendidos.
A6: Checklist | B6: Lista de tópicos. Altere a coluna Status (lista suspensa) e preencha as datas. Tópicos concluídos ficam riscados.
A7: Diario | B7: Registre cada sessão de estudo: data, ID do tópico (lista), horas e o que aprendeu. As horas somam no Checklist e no Painel.
A8: Cronograma | B8: Plano de 8 semanas. Altere a data de início (célula C3) e as datas das semanas se ajustam.
A10: CONVENÇÕES
A11: Fundo amarelo | B11: Células para você preencher (Status, datas, observações, diário).
A12: Texto azul | B12: Valores digitados por você. Texto preto = fórmulas (não altere).
A13: Status | B13: Não iniciado · Estudando · Revisar · Concluído
A14: Nível | B14: Básico (verde) · Intermediário (amarelo) · Avançado (vermelho)
A15: Pacotes | B15: 1, 2, 3, 4 = pacotes do portfólio · E = Extras · Todos = vale para todos os pacotes
A17: DICA | B17: Marque como Concluído só depois de fazer o Exercício Prático na base de e-commerce. Use 'Revisar' para tópicos que precisam de reforço.
A18: Novo tópico | B18: Adicione uma linha no final da tabela do Checklist (ela se expande sozinha) com um novo ID, ex.: T62.

Sheet Checklist
A1: ID | B1: Semana | C1: Bloco | D1: Pacotes | E1: Tópico | F1: Nível | G1: Status | H1: Data_Inicio | I1: Data_Conclusao | J1: Horas_Estudadas | K1: Fonte_Sugerida | L1: Exercicio_Pratico | M1: Observacoes
A2: T01 | B2: 1 | C2: Excel | D2: 1 | E2: Tabelas formatadas (Ctrl+T) e boas práticas de nomes de colunas | F2: Básico | G2: Não iniciado | J2: =SUMIFS(Diario!$D:$D,Diario!$B:$B,A2) -> 0 | K2: Microsoft Learn / Hashtag | L2: Converter dClientes em tabela e renomear colunas
A3: T02 | B3: 1 | C3: Excel | D3: 1 | E3: Remover duplicadas (escolhendo as colunas-chave) | F3: Básico | G3: Não iniciado | J3: =SUMIFS(Diario!$D:$D,Diario!$B:$B,A3) -> 0 | K3: Hashtag Treinamentos | L3: Base_Suja: remover clientes repetidos
A4: T03 | B4: 1 | C4: Excel | D4: 1 | E4: Funções de texto: ARRUMAR, PRI.MAIÚSCULA, SUBSTITUIR, ESQUERDA/DIREITA/EXT.TEXTO | F4: Básico | G4: Não iniciado | J4: =SUMIFS(Diario!$D:$D,Diario!$B:$B,A4) -> 0 | K4: Hashtag Treinamentos | L4: Base_Suja: padronizar NOME CLIENTE e cidade
A5: T04 | B5: 1 | C5: Excel | D5: 1 | E5: Texto para Colunas, TEXTOANTES/TEXTODEPOIS, concatenar | F5: Básico | G5: Não iniciado | J5: =SUMIFS(Diario!$D:$D,Diario!$B:$B,A5) -> 0 | K5: Hashtag Treinamentos | L5: Separar nome e sobrenome em dClientes
A6: T05 | B6: 1 | C6: Excel | D6: 1,2 | E6: Funções de data: HOJE, DATA, MÊS, ANO, FIMMÊS, DATADIF, DIATRABALHOTOTAL | F6: Básico | G6: Não iniciado | J6: =SUMIFS(Diario!$D:$D,Diario!$B:$B,A6) -> 0 | K6: Microsoft Learn | L6: Calcular tempo de cadastro dos clientes
A7: T06 | B7: 1 | C7: Excel | D7: 1,2 | E7: Funções lógicas: SE, SES, E, OU, SEERRO | F7: Básico | G7: Não iniciado | J7: =SUMIFS(Diario!$D:$D,Diario!$B:$B,A7) -> 0 | K7: Hashtag Treinamentos | L7: Classificar pedidos por faixa de valor
A8: T07 | B8: 1 | C8: Excel | D8: 2 | E8: Referências relativas e absolutas ($) | F8: Básico | G8: Não iniciado | J8: =SUMIFS(Diario!$D:$D,Diario!$B:$B,A8) -> 0 | K8: Hashtag Treinamentos | L8: Montar tabela de faturamento por mês
A9: T08 | B9: 2 | C9: Excel | D9: 2 | E9: PROCX e ÍNDICE + CORRESP | F9: Intermediário | G9: Não iniciado | J9: =SUMIFS(Diario!$D:$D,Diario!$B:$B,A9) -> 0 | K9: Hashtag Treinamentos | L9: Trazer a Categoria do produto para fVendas
A10: T09 | B10: 2 | C10: Excel | D10: 2 | E10: SOMASES, CONT.SES, MÉDIASES com critérios de data | F10: Intermediário | G10: Não iniciado | J10: =SUMIFS(Diario!$D:$D,Diario!$B:$B,A10) -> 0 | K10: Hashtag Treinamentos | L10: Refazer os KPIs da aba Resumo
A11: T10 | B11: 2 | C11: Excel | D11: 1,2 | E11: Tabela dinâmica: linhas, colunas, valores, filtros | F11: Básico | G11: Não iniciado | J11: =SUMIFS(Diario!$D:$D,Diario!$B:$B,A11) -> 0 | K11: Microsoft Learn | L11: Faturamento por Categoria x Canal
A12: T11 | B12: 2 | C12: Excel | D12: 2 | E12: Gráfico dinâmico, Segmentação de Dados e Linha do Tempo | F12: Intermediário | G12: Não iniciado | J12: =SUMIFS(Diario!$D:$D,Diario!$B:$B,A12) -> 0 | K12: Karine Lago | L12: Gráfico mensal com segmentação por canal
A13: T12 | B13: 2 | C13: Excel | D13: 2 | E13: Formatação condicional (regras, barras de dados, ícones) | F13: Básico | G13: Não iniciado | J13: =SUMIFS(Diario!$D:$D,Diario!$B:$B,A13) -> 0 | K13: Hashtag Treinamentos | L13: Alerta de estoque na aba fEstoque
... A62: T61 | B62: 8 | C62: Python | D62: E | E62: Agendar scripts no Agendador de Tarefas do Windows | F62: Básico | G62: Não iniciado | J62: =SUMIFS(Diario!$D:$D,Diario!$B:$B,A62) -> 0 | K62: Microsoft Docs | L62: Agendar o gerar_base.py

Sheet Diario
A1: Data | B1: ID_Topico | C1: Topico (automático) | D1: Horas | E1: O que aprendi / dúvidas
A2: 46315 | B2: T01 | C2: =IFERROR(INDEX(Checklist!$E:$E,MATCH(B2,Checklist!$A:$A,0)),"") -> Tabelas formatadas (Ctrl+T) e boas práticas de nomes de colunas | D2: 0 | E2: EXEMPLO – substitua por um registro real (horas = 0 para não contar)
C3: =IF(B3="","",IFERROR(INDEX(Checklist!$E:$E,MATCH(B3,Checklist!$A:$A,0)),"ID não encontrado"))
C4: =IF(B4="","",IFERROR(INDEX(Checklist!$E:$E,MATCH(B4,Checklist!$A:$A,0)),"ID não encontrado"))
C5: =IF(B5="","",IFERROR(INDEX(Checklist!$E:$E,MATCH(B5,Checklist!$A:$A,0)),"ID não encontrado"))
C6: =IF(B6="","",IFERROR(INDEX(Checklist!$E:$E,MATCH(B6,Checklist!$A:$A,0)),"ID não encontrado"))
C7: =IF(B7="","",IFERROR(INDEX(Checklist!$E:$E,MATCH(B7,Checklist!$A:$A,0)),"ID não encontrado"))
C8: =IF(B8="","",IFERROR(INDEX(Checklist!$E:$E,MATCH(B8,Checklist!$A:$A,0)),"ID não encontrado"))
C9: =IF(B9="","",IFERROR(INDEX(Checklist!$E:$E,MATCH(B9,Checklist!$A:$A,0)),"ID não encontrado"))
C10: =IF(B10="","",IFERROR(INDEX(Checklist!$E:$E,MATCH(B10,Checklist!$A:$A,0)),"ID não encontrado"))
C11: =IF(B11="","",IFERROR(INDEX(Checklist!$E:$E,MATCH(B11,Checklist!$A:$A,0)),"ID não encontrado"))
C12: =IF(B12="","",IFERROR(INDEX(Checklist!$E:$E,MATCH(B12,Checklist!$A:$A,0)),"ID não encontrado"))
C13: =IF(B13="","",IFERROR(INDEX(Checklist!$E:$E,MATCH(B13,Checklist!$A:$A,0)),"ID não encontrado"))
C14: =IF(B14="","",IFERROR(INDEX(Checklist!$E:$E,MATCH(B14,Checklist!$A:$A,0)),"ID não encontrado"))
... C400: =IF(B400="","",IFERROR(INDEX(Checklist!$E:$E,MATCH(B400,Checklist!$A:$A,0)),"ID não encontrado"))

Sheet Cronograma
A1: Cronograma de 8 semanas (1 a 2 h por dia)
A3: Data de início do estudo: | C3: 46321 | D3: ← altere para a sua data (segunda-feira)
A5: Semana | B5: Início | C5: Fim | D5: Foco | E5: Libera | F5: Tópicos | G5: Concluídos | H5: % Semana
A6: 1 | B6: =$C$3+7*(A6-1) -> 46321 | C6: =B6+6 -> 46327 | D6: Excel: tabelas, fórmulas básicas, texto, data, lógica | E6: — | F6: =COUNTIF(Checklist!$B$2:$B$62,A6) -> 7 | G6: =COUNTIFS(Checklist!$B$2:$B$62,A6,Checklist!$G$2:$G$62,"Concluído") -> 0 | H6: =IF(F6=0,0,G6/F6) -> 0
A7: 2 | B7: =$C$3+7*(A7-1) -> 46328 | C7: =B7+6 -> 46334 | D7: Excel: PROCX, SOMASES, tabela dinâmica, formatação condicional | E7: Pacotes 1 e 2 (Básico) | F7: =COUNTIF(Checklist!$B$2:$B$62,A7) -> 7 | G7: =COUNTIFS(Checklist!$B$2:$B$62,A7,Checklist!$G$2:$G$62,"Concluído") -> 0 | H7: =IF(F7=0,0,G7/F7) -> 0
A8: 3 | B8: =$C$3+7*(A8-1) -> 46335 | C8: =B8+6 -> 46341 | D8: Power Query + AMOSTRA 1 | E8: Pacote 1 completo | F8: =COUNTIF(Checklist!$B$2:$B$62,A8) -> 9 | G8: =COUNTIFS(Checklist!$B$2:$B$62,A8,Checklist!$G$2:$G$62,"Concluído") -> 0 | H8: =IF(F8=0,0,G8/F8) -> 0
A9: 4 | B9: =$C$3+7*(A9-1) -> 46342 | C9: =B9+6 -> 46348 | D9: Painel no Excel, KPIs de e-commerce, pandas + AMOSTRA 2 | E9: Pacote 2 completo | F9: =COUNTIF(Checklist!$B$2:$B$62,A9) -> 8 | G9: =COUNTIFS(Checklist!$B$2:$B$62,A9,Checklist!$G$2:$G$62,"Concluído") -> 0 | H9: =IF(F9=0,0,G9/F9) -> 0
A10: 5 | B10: =$C$3+7*(A10-1) -> 46349 | C10: =B10+6 -> 46355 | D10: Power BI: interface, modelagem estrela, visuais | E10: Pacote 3 (Básico) | F10: =COUNTIF(Checklist!$B$2:$B$62,A10) -> 7 | G10: =COUNTIFS(Checklist!$B$2:$B$62,A10,Checklist!$G$2:$G$62,"Concluído") -> 0 | H10: =IF(F10=0,0,G10/F10) -> 0
A11: 6 | B11: =$C$3+7*(A11-1) -> 46356 | C11: =B11+6 -> 46362 | D11: DAX: básico, CALCULATE, iteradores + SQL | E11: Pacote 3 (Padrão) | F11: =COUNTIF(Checklist!$B$2:$B$62,A11) -> 6 | G11: =COUNTIFS(Checklist!$B$2:$B$62,A11,Checklist!$G$2:$G$62,"Concluído") -> 0 | H11: =IF(F11=0,0,G11/F11) -> 0
A12: 7 | B12: =$C$3+7*(A12-1) -> 46363 | C12: =B12+6 -> 46369 | D12: DAX de tempo, ranking, tema, drill-through + AMOSTRA 3 | E12: Pacote 3 (Padrão) | F12: =COUNTIF(Checklist!$B$2:$B$62,A12) -> 7 | G12: =COUNTIFS(Checklist!$B$2:$B$62,A12,Checklist!$G$2:$G$62,"Concluído") -> 0 | H12: =IF(F12=0,0,G12/F12) -> 0
A13: 8 | B13: =$C$3+7*(A13-1) -> 46370 | C13: =B13+6 -> 46376 | D13: Power BI Service, Gateway, RLS, manutenção, LGPD | E13: Pacote 3 Premium + Pacote 4 | F13: =COUNTIF(Checklist!$B$2:$B$62,A13) -> 10 | G13: =COUNTIFS(Checklist!$B$2:$B$62,A13,Checklist!$G$2:$G$62,"Concluído") -> 0 | H13: =IF(F13=0,0,G13/F13) -> 0
